covdrugsim/__init__.py
covdrugsim/data/__init__.py
covdrugsim/data/chargesExample.txt
covdrugsim/data/energyLevellerExample.inp
covdrugsim/data/exampleGaussianOutputs/example1.out
covdrugsim/data/exampleGaussianOutputs/example2.out
covdrugsim/data/exampleGaussianOutputs/example3.out
covdrugsim/data/exampleXYZs/example1.xyz
covdrugsim/data/exampleXYZs/example2.xyz
covdrugsim/data/exampleXYZs/example3.xyz
covdrugsim/datasets.py
covdrugsim/main.py
covdrugsim/mdsim/SCbondDist.py
covdrugsim/mdsim/__init__.py
covdrugsim/mdsim/baseID.py
covdrugsim/mdsim/bbRMSD.py
covdrugsim/mdsim/config.py
covdrugsim/mdsim/hbondAnalysis.py
covdrugsim/mdsim/ligDihedral.py
covdrugsim/mdsim/mdAnalyse.py
covdrugsim/mdsim/prepMTB.py
covdrugsim/qmcalc/__init__.py
covdrugsim/qmcalc/admin.py
covdrugsim/qmcalc/constants.py
covdrugsim/qmcalc/genScripts.py
covdrugsim/qmcalc/gsub.sh
covdrugsim/qmcalc/tabulate.py
covdrugsim/qmcalc/unitConv.py
covdrugsim/qmcalc/visAnalysis/__init__.py
covdrugsim/qmcalc/visAnalysis/energyLeveller.py
covdrugsim/qmcalc/visAnalysis/plotConfig.py
covdrugsim/qmcalc/visAnalysis/plotFigs.py
covdrugsim-1.0.22.dist-info/LICENSE
covdrugsim-1.0.22.dist-info/METADATA
covdrugsim-1.0.22.dist-info/WHEEL
covdrugsim-1.0.22.dist-info/RECORD
