Metadata-Version: 2.3
Name: covdrugsim
Version: 1.0.22
Summary: Package to automate quantum mechanical calculations and molecular dynamics simulations of covalent drugs.
License: MIT
Keywords: covalent,drug,quantum,mechanic,molecular,dynamics,simulation
Author: Jonathan Yik Chang Ting
Author-email: jonting97@gmail.com
Requires-Python: >=3.9
Classifier: Intended Audience :: Science/Research
Classifier: License :: OSI Approved :: MIT License
Classifier: Natural Language :: English
Classifier: Operating System :: OS Independent
Classifier: Programming Language :: Python :: 3
Classifier: Programming Language :: Python :: 3.9
Classifier: Programming Language :: Python :: 3.10
Classifier: Programming Language :: Python :: 3.11
Classifier: Programming Language :: Python :: 3.12
Classifier: Programming Language :: Python :: 3.13
Classifier: Topic :: Scientific/Engineering
Requires-Dist: matplotlib (>=3.7.1)
Requires-Dist: numpy (>=1.25.0)
Requires-Dist: pandas (>=2.0.2)
Requires-Dist: seaborn (>=0.12.2)
Project-URL: Documentation, https://covdrugsim.readthedocs.io/en/latest/
Project-URL: Homepage, https://github.com/Jon-Ting/covdrugsim
Project-URL: Repository, https://github.com/Jon-Ting/covdrugsim
